LICENSE.txt
README.md
setup.py
acm/__init__.py
acm/base_code.py
acm/oj.py
sdtbu_acm_tool.egg-info/PKG-INFO
sdtbu_acm_tool.egg-info/SOURCES.txt
sdtbu_acm_tool.egg-info/dependency_links.txt
sdtbu_acm_tool.egg-info/entry_points.txt
sdtbu_acm_tool.egg-info/requires.txt
sdtbu_acm_tool.egg-info/top_level.txt