Metadata-Version: 2.1
Name: sdtbu-acm-tool
Version: 1.0.5
Summary: 一些实用工具
Home-page: UNKNOWN
Author: 曾钦李
Author-email: 1838696034@qq.com
Maintainer: 
Maintainer-email: 
License: MIT License
Platform: UNKNOWN
Classifier: Topic :: Software Development :: Build Tools
Classifier: License :: OSI Approved :: MIT License
Classifier: Programming Language :: Python :: 3
Requires-Python: >=3.6
License-File: LICENSE.txt
